vezda/LinearOperators.py
vezda/LinearSamplingClass.py
vezda/Morozov.py
vezda/Picard.py
vezda/Solve.py
vezda/VirtualExperiment.py
vezda/__init__.py
vezda/addNoise.py
vezda/data_utils.py
vezda/home.py
vezda/math_utils.py
vezda/plotImage.py
vezda/plotSVD.py
vezda/plotSpectra.py
vezda/plotWiggles.py
vezda/plot_utils.py
vezda/sampling_utils.py
vezda/setDataPath.py
vezda/setSearchGrid.py
vezda/setWindow.py
vezda/signal_utils.py
vezda/svd_utils.py
vezda/docs/UserManual.pdf
vezda/examples/.DS_Store
vezda/examples/starfish-tutorial/.DS_Store
vezda/examples/starfish-tutorial/data/extractData.py
vezda/examples/starfish-tutorial/data/starfish.mat
vezda/examples/starfish-tutorial/tutorial1/.DS_Store
vezda/examples/starfish-tutorial/tutorial1/README.md
vezda/examples/starfish-tutorial/tutorial1/pulseFun.py
vezda/examples/starfish-tutorial/tutorial1/figures/data1.png
vezda/examples/starfish-tutorial/tutorial1/figures/data1map.png
vezda/examples/starfish-tutorial/tutorial1/figures/data1window.png
vezda/examples/starfish-tutorial/tutorial1/figures/experimentalSetup.png
vezda/examples/starfish-tutorial/tutorial1/figures/experimentalSetup2.png
vezda/examples/starfish-tutorial/tutorial1/figures/invx.png
vezda/examples/starfish-tutorial/tutorial1/figures/norecxy.png
vezda/examples/starfish-tutorial/tutorial1/figures/reconstruction.png
vezda/examples/starfish-tutorial/tutorial1/figures/singularValues.png
vezda/examples/starfish-tutorial/tutorial1/figures/testFunc.png
vezda/examples/starfish-tutorial/tutorial1/figures/withScat.png
vezda/examples/starfish-tutorial/tutorial2/README.md
vezda/examples/starfish-tutorial/tutorial2/pulseFun.py
vezda/examples/starfish-tutorial/tutorial2/figures/data1map.png
vezda/examples/starfish-tutorial/tutorial2/figures/eswind.png
vezda/examples/starfish-tutorial/tutorial2/figures/experimentalSetup.png
vezda/examples/starfish-tutorial/tutorial2/figures/exs1.png
vezda/examples/starfish-tutorial/tutorial2/figures/exs2.png
vezda-0.6.7.dist-info/LICENSE
vezda-0.6.7.dist-info/METADATA
vezda-0.6.7.dist-info/WHEEL
vezda-0.6.7.dist-info/entry_points.txt
vezda-0.6.7.dist-info/top_level.txt
vezda-0.6.7.dist-info/RECORD
